linky/VERSION
linky/__init__.py
linky/app.py
linky/config.py
linky/actions/__init__.py
linky/actions/add.py
linky/actions/init.py
linky/actions/move.py
linky/actions/remove.py
linky/actions/tag.py
linky/actions/tags.py
linky/commands/__init__.py
linky/commands/add.py
linky/commands/init.py
linky/commands/move.py
linky/commands/remove.py
linky/commands/tag.py
linky/commands/tags.py
linky/schemas/categories.schema.yaml
linky/schemas/custom_tags.schema.yaml
linky/schemas/main.schema.yaml
linky/utils/__init__.py
linky/utils/dupe_handlers.py
linky/utils/library_utils.py
linky/utils/path_utils.py
linky/utils/str_utils.py
linky_db-1.5.0.dist-info/LICENSE
linky_db-1.5.0.dist-info/METADATA
linky_db-1.5.0.dist-info/WHEEL
linky_db-1.5.0.dist-info/entry_points.txt
linky_db-1.5.0.dist-info/top_level.txt
linky_db-1.5.0.dist-info/RECORD
