Metadata-Version: 2.1
Name: linky-db
Version: 1.5.0
Summary: A script to manage and tag files using symlinks
Home-page: https://gitlab.com/NamingThingsIsHard/linky
Author: LoveIsGrief
Author-email: loveisgrief@tuta.io
Project-URL: Bug Tracker, https://gitlab.com/NamingThingsIsHard/linky/issues
Classifier: Programming Language :: Python :: 3
Classifier: License :: OSI Approved :: Mozilla Public License 2.0 (MPL 2.0)
Classifier: Operating System :: POSIX :: Linux
License-File: LICENSE
Requires-Dist: cliff ==3.7.0
Requires-Dist: yamale ==2.0.1
